{"commit":"4e7e2f5d7940a711b59f89190b5b7e3029f050f5","pagesAndArtboards":{"10BCBBDE-CD11-4DC7-AEF9-0F643754D971":{"name":"Resume Copy","artboards":{"A1E0CF05-2F3B-46F1-A678-2B62A898F8CE":{"name":"Page 1"},"3032C017-F941-4DA8-A6BD-1D270435EFAA":{"name":"Page 1 Copy"}}}},"version":103,"fonts":["BreeSerif-Regular","Tahoma","AvenirNext-Medium","AvenirNext-Regular"],"compatibilityVersion":99,"app":"com.bohemiancoding.sketch3","autosaved":0,"variant":"NONAPPSTORE","created":{"commit":"4e7e2f5d7940a711b59f89190b5b7e3029f050f5","appVersion":"50.2","build":55047,"app":"com.bohemiancoding.sketch3","compatibilityVersion":99,"version":103,"variant":"NONAPPSTORE"},"saveHistory":["NONAPPSTORE.55047"],"appVersion":"50.2","build":55047}